typium/__init__.py
typium-0.0.1.dev0.dist-info/LICENSE
typium-0.0.1.dev0.dist-info/METADATA
typium-0.0.1.dev0.dist-info/WHEEL
typium-0.0.1.dev0.dist-info/top_level.txt
typium-0.0.1.dev0.dist-info/RECORD
