Metadata-Version: 2.1
Name: typium
Version: 0.0.1.dev0
Summary: Description will be soon
Home-page: https://github.com/ttarker/typium
Author: Artem Popov
Author-email: mr.tarker@yandex.ru
License: Apache-2.0
Platform: UNKNOWN
License-File: LICENSE
